nested_search/__init__.py
nested_search/nested_search.py
nested_search-0.0.2.data/scripts/nested_search.py
nested_search-0.0.2.dist-info/METADATA
nested_search-0.0.2.dist-info/WHEEL
nested_search-0.0.2.dist-info/top_level.txt
nested_search-0.0.2.dist-info/RECORD
