Metadata-Version: 2.1
Name: nested-search
Version: 0.0.2
Summary: Utility to deep search and compare two JSON string
Home-page: 
Author: Technical Coder
Author-email: Technical Coder <techcoder2125@gmail.com>
Classifier: Programming Language :: Python :: 3
Classifier: License :: OSI Approved :: MIT License
Classifier: Operating System :: OS Independent
Requires-Python: >=3.7
